LICENSE
kerastuner_tensorboard_logger/__init__.py
kerastuner_tensorboard_logger/initialize.py
kerastuner_tensorboard_logger/logger.py
kerastuner_tensorboard_logger-0.2.3.dist-info/LICENSE
kerastuner_tensorboard_logger-0.2.3.dist-info/WHEEL
kerastuner_tensorboard_logger-0.2.3.dist-info/METADATA
kerastuner_tensorboard_logger-0.2.3.dist-info/RECORD
