Metadata-Version: 2.1
Name: kerastuner-tensorboard-logger
Version: 0.2.3
Summary: Simple integration of keras-tuner (hyperparameter tuning) and tensorboard dashboard (interactive visualization).
Home-page: https://github.com/tokusumi/kerastuner-tensorboard-logger
License: MIT
Keywords: tensorflow2,keras-tuner,tensorboard
Author: tokusumi
Author-email: tksmtoms@gmail.com
Requires-Python: >=3.6,<4.0
Classifier: License :: OSI Approved :: MIT License
Classifier: Operating System :: OS Independent
Classifier: Programming Language :: Python :: 3
Classifier: Programming Language :: Python :: 3 :: Only
Classifier: Programming Language :: Python :: 3.6
Classifier: Programming Language :: Python :: 3.7
Classifier: Programming Language :: Python :: 3.8
Classifier: Topic :: Scientific/Engineering :: Artificial Intelligence
Requires-Dist: keras-tuner (>=1.0,<2.0)
Requires-Dist: tensorflow (>=2.0,<3.0)
Project-URL: Repository, https://github.com/tokusumi/kerastuner-tensorboard-logger
